<?xml version="1.0" encoding="UTF-8"?><record_update>
    <sys_dictionary action="DELETE" element="department" table="x_isgi_roster_calendar">
        <active>true</active>
        <array>false</array>
        <array_denormalized>false</array_denormalized>
        <attributes>edge_encryption_enabled=true</attributes>
        <audit>false</audit>
        <calculation/>
        <choice>0</choice>
        <choice_field/>
        <choice_table/>
        <column_label>Department</column_label>
        <comments/>
        <create_roles/>
        <default_value/>
        <defaultsort/>
        <delete_roles/>
        <dependent/>
        <dependent_on_field/>
        <display>false</display>
        <dynamic_creation>false</dynamic_creation>
        <dynamic_creation_script/>
        <dynamic_default_value/>
        <dynamic_ref_qual/>
        <element>department</element>
        <element_reference>false</element_reference>
        <foreign_database/>
        <function_definition/>
        <function_field>false</function_field>
        <internal_type display_value="String">string</internal_type>
        <mandatory>false</mandatory>
        <max_length>40</max_length>
        <name>x_isgi_roster_calendar</name>
        <next_element/>
        <primary>false</primary>
        <read_only>true</read_only>
        <read_roles/>
        <reference/>
        <reference_cascade_rule/>
        <reference_floats>false</reference_floats>
        <reference_key/>
        <reference_qual/>
        <reference_qual_condition/>
        <reference_type/>
        <sizeclass/>
        <spell_check>false</spell_check>
        <staged>false</staged>
        <sys_class_name>sys_dictionary</sys_class_name>
        <sys_created_by>mohamed.rafiulla@isg-one.com</sys_created_by>
        <sys_created_on>2020-10-20 06:49:34</sys_created_on>
        <sys_customer_update>false</sys_customer_update>
        <sys_id>29126df81b986410af1ef436464bcb9f</sys_id>
        <sys_mod_count>0</sys_mod_count>
        <sys_name>Department</sys_name>
        <sys_package display_value="roster" source="x_isgi_roster">3f44a5b11b739c149d4e6392f54bcbbf</sys_package>
        <sys_policy/>
        <sys_replace_on_upgrade>false</sys_replace_on_upgrade>
        <sys_scope display_value="roster">3f44a5b11b739c149d4e6392f54bcbbf</sys_scope>
        <sys_update_name>sys_dictionary_x_isgi_roster_calendar_department</sys_update_name>
        <sys_updated_by>mohamed.rafiulla@isg-one.com</sys_updated_by>
        <sys_updated_on>2020-11-03 04:40:31</sys_updated_on>
        <table_reference>false</table_reference>
        <text_index>false</text_index>
        <unique>false</unique>
        <use_dependent_field>false</use_dependent_field>
        <use_dynamic_default>false</use_dynamic_default>
        <use_reference_qualifier>simple</use_reference_qualifier>
        <virtual>false</virtual>
        <widget/>
        <write_roles/>
        <xml_view>false</xml_view>
    </sys_dictionary>
<sys_update_version action="INSERT_OR_UPDATE">
        <action>DELETE</action>
        <application display_value="roster">3f44a5b11b739c149d4e6392f54bcbbf</application>
        <file_path/>
        <instance_id>69a78f219b99cb447ac36b8af359ff47</instance_id>
        <instance_name>isggoverndev4</instance_name>
        <name>sys_dictionary_x_isgi_roster_calendar_department</name>
        <payload><![CDATA[<?xml version="1.0" encoding="UTF-8"?><record_update>
    <sys_dictionary action="INSERT_OR_UPDATE" element="department" table="x_isgi_roster_calendar">
        <active>true</active>
        <array>false</array>
        <array_denormalized>false</array_denormalized>
        <attributes>edge_encryption_enabled=true</attributes>
        <audit>false</audit>
        <calculation/>
        <choice>0</choice>
        <choice_field/>
        <choice_table/>
        <column_label>Department</column_label>
        <comments/>
        <create_roles/>
        <default_value/>
        <defaultsort/>
        <delete_roles/>
        <dependent/>
        <dependent_on_field/>
        <display>false</display>
        <dynamic_creation>false</dynamic_creation>
        <dynamic_creation_script/>
        <dynamic_default_value/>
        <dynamic_ref_qual/>
        <element>department</element>
        <element_reference>false</element_reference>
        <foreign_database/>
        <function_definition/>
        <function_field>false</function_field>
        <internal_type display_value="String">string</internal_type>
        <mandatory>false</mandatory>
        <max_length>40</max_length>
        <name>x_isgi_roster_calendar</name>
        <next_element/>
        <primary>false</primary>
        <read_only>true</read_only>
        <read_roles/>
        <reference/>
        <reference_cascade_rule/>
        <reference_floats>false</reference_floats>
        <reference_key/>
        <reference_qual/>
        <reference_qual_condition/>
        <reference_type/>
        <sizeclass/>
        <spell_check>false</spell_check>
        <staged>false</staged>
        <sys_class_name>sys_dictionary</sys_class_name>
        <sys_created_by>mohamed.rafiulla@isg-one.com</sys_created_by>
        <sys_created_on>2020-10-20 06:49:34</sys_created_on>
        <sys_customer_update>false</sys_customer_update>
        <sys_id>29126df81b986410af1ef436464bcb9f</sys_id>
        <sys_mod_count>0</sys_mod_count>
        <sys_name>Department</sys_name>
        <sys_package display_value="roster" source="x_isgi_roster">3f44a5b11b739c149d4e6392f54bcbbf</sys_package>
        <sys_policy/>
        <sys_replace_on_upgrade>false</sys_replace_on_upgrade>
        <sys_scope display_value="roster">3f44a5b11b739c149d4e6392f54bcbbf</sys_scope>
        <sys_update_name>sys_dictionary_x_isgi_roster_calendar_department</sys_update_name>
        <sys_updated_by>mohamed.rafiulla@isg-one.com</sys_updated_by>
        <sys_updated_on>2020-11-03 04:40:31</sys_updated_on>
        <table_reference>false</table_reference>
        <text_index>false</text_index>
        <unique>false</unique>
        <use_dependent_field>false</use_dependent_field>
        <use_dynamic_default>false</use_dynamic_default>
        <use_reference_qualifier>simple</use_reference_qualifier>
        <virtual>false</virtual>
        <widget/>
        <write_roles/>
        <xml_view>false</xml_view>
    </sys_dictionary>
</record_update>]]></payload>
        <payload_hash>1028157569</payload_hash>
        <record_name>Calendar.Department</record_name>
        <reverted_from/>
        <source>509da5f01b1c6410af1ef436464bcb09</source>
        <source_table>sys_upgrade_history</source_table>
        <state>previous</state>
        <sys_created_by>mohamed.rafiulla@isg-one.com</sys_created_by>
        <sys_created_on>2020-11-03 05:31:12</sys_created_on>
        <sys_id>cdbda5341b1c6410af1ef436464bcb22</sys_id>
        <sys_mod_count>0</sys_mod_count>
        <sys_recorded_at>1758c9675a90000001</sys_recorded_at>
        <sys_updated_by>mohamed.rafiulla@isg-one.com</sys_updated_by>
        <sys_updated_on>2020-11-03 05:31:12</sys_updated_on>
        <type>Dictionary</type>
        <update_guid>0dbda534171c6410306e3c376aed0522</update_guid>
        <update_guid_history>0dbda534171c6410306e3c376aed0522:0,acad6df0811c64102efc806efe7bd72d:-1690757539,7612edf855986410dacc3ec4134d7592:0,0e0269f82e986410be858bda7260482b:-1690757539,f4b121b8a49864102a54824e0b04e2b1:0,af912978de986410a67827fc6c8abb0d:-1690757539,b46931d0e6006c5435c0d01e5025e003:-1887447383,3c69fd90d3006c54c50b1497b6362bbc:1038751384</update_guid_history>
    </sys_update_version>
    <sys_metadata_delete action="INSERT_OR_UPDATE">
        <sys_audit_delete/>
        <sys_class_name>sys_metadata_delete</sys_class_name>
        <sys_created_by>SaiThulasi.Kaditham@isg-one.com</sys_created_by>
        <sys_created_on>2020-12-02 02:43:53</sys_created_on>
        <sys_customer_update>false</sys_customer_update>
        <sys_db_object display_value="" name="sys_dictionary">sys_dictionary</sys_db_object>
        <sys_id>12c253fc96994db48610bd910628ff90</sys_id>
        <sys_metadata>7fade1341b1c6410af1ef436464bcba6</sys_metadata>
        <sys_mod_count>0</sys_mod_count>
        <sys_name>Department</sys_name>
        <sys_package display_value="roster" source="x_isgi_roster">3f44a5b11b739c149d4e6392f54bcbbf</sys_package>
        <sys_parent display_value="Calendar">e587f1101b006c549d4e6392f54bcb6e</sys_parent>
        <sys_policy/>
        <sys_replace_on_upgrade>false</sys_replace_on_upgrade>
        <sys_scope display_value="roster">3f44a5b11b739c149d4e6392f54bcbbf</sys_scope>
        <sys_scope_delete display_value="">94aba01e32774c00ad01831d23410000</sys_scope_delete>
        <sys_update_name>sys_dictionary_x_isgi_roster_calendar_department</sys_update_name>
        <sys_update_version display_value="sys_dictionary_x_isgi_roster_calendar_department">cdbda5341b1c6410af1ef436464bcb22</sys_update_version>
        <sys_updated_by>SaiThulasi.Kaditham@isg-one.com</sys_updated_by>
        <sys_updated_on>2020-12-02 02:43:53</sys_updated_on>
    </sys_metadata_delete>
</record_update>
